{
  "romname":"ace",
  "ports":{
    ":c00a":{
      "labels":{
        "1":{"name":"P1 Left","player":0}
      }
    },
    ":c00b":{
      "labels":{
        "1":{"name":"P1 Right","player":0}
      }
    },
    ":c00e":{
      "labels":{
        "1":{"name":"P2 Slow Down","player":1}
      }
    },
    ":c011":{
      "labels":{
        "1":{"name":"P2 Fire","player":1}
      }
    },
    ":c010":{
      "labels":{
        "1":{"name":"P2 Right","player":1}
      }
    },
    ":c009":{
      "labels":{
        "1":{"name":"P1 Slow Down","player":0}
      }
    },
    ":c008":{
      "labels":{
        "1":{"name":"P1 Speed Up","player":0}
      }
    },
    ":c00f":{
      "labels":{
        "1":{"name":"P2 Left","player":1}
      }
    },
    ":c00c":{
      "labels":{
        "1":{"name":"P1 Fire","player":0}
      }
    },
    ":c00d":{
      "labels":{
        "1":{"name":"P2 Speed Up","player":1}
      }
    }
  }
}