{
  "romname":"doa2m",
  "ports":{
    ":P1":{
      "labels":{
        "10":{"player":0,"name":"P1 ..."},
        "20":{"player":0,"name":"P1 ..."},
        "40":{"player":0,"name":"P1 ..."},
        "80":{"player":0,"name":"P1 Guard"},
        "100":{"player":0,"name":"P1 Kick"},
        "200":{"player":0,"name":"P1 Punch"}
      }
    },
    ":P2":{
      "labels":{
        "10":{"player":1,"name":"P2 ..."},
        "20":{"player":1,"name":"P2 ..."},
        "40":{"player":1,"name":"P2 ..."},
        "80":{"player":1,"name":"P2 Guard"},
        "100":{"player":1,"name":"P2 Kick"},
        "200":{"player":1,"name":"P2 Punch"}
      }
    }
  }
}