{
  "romname":"harley",
  "ports":{
    ":AN0":{
      "labels":{
        "ff":{"player":0,"name":"Paddle"}
      }
    },
    ":AN1":{
      "labels":{
        "ff":{"player":0,"name":"P1 Pedal 1"}
      }
    },
    ":AN2":{
      "labels":{
        "ff":{"player":0,"name":"P1 Pedal 2"}
      }
    },
    ":AN3":{
      "labels":{
        "ff":{"player":0,"name":"P1 Pedal 3"}
      }
    },
    ":IN0":{
      "labels":{
        "1":{"player":0,"name":"Coin 1"},
        "2":{"player":0,"name":"Coin 2"},
        "4":{"player":0,"name":"Service Mode"},
        "8":{"player":0,"name":"Service 1"},
        "10":{"player":0,"name":"1 Player Start"},
        "20":{"player":0,"name":"2 Players Start"}
      }
    },
    ":IN1":{
      "labels":{
        "40":{"player":0,"name":"Service Button B"},
        "80":{"player":0,"name":"Test Button B"}
      }
    },
    ":IN2":{
      "labels":{
        "1":{"player":0,"name":"P1 Button 1"},
        "2":{"player":0,"name":"P1 Button 2"},
        "10":{"player":0,"name":"P1 Button 3"},
        "20":{"player":0,"name":"P1 Button 4"}
      }
    }
  }
}